{
  "project_info": {
    "name": "AI智能体辅助数学教学工具",
    "version": "1.0.0",
    "creation_date": "2025-12-08",
    "description": "基于MCP的数学教学辅助系统，包含GeoGebra集成、数学可视化、智能练习题生成、公式转换和分步教程功能"
  },
  "development_process": {
    "initial_problem": {
      "user_request": "帮我在这个mcp中集成一个按照指令搜索网页，自动生成符合要求的geogebra演示图像，动画的功能 geogebra已经在本地完成了下载",
      "geogebra_path": "C:\\Users\\rog\\Desktop\\GeoGebra_Calculator\\app-6.0.8990",
      "issue": "在最后的测试阶段iflow卡死了"
    },
    "diagnosis": {
      "crash_causes": [
        "Canvas缓冲区未释放：canvas.toBuffer()在Windows环境下可能阻塞主线程",
        "缺少文件系统写入：生成的图像缓冲区没有写入磁盘，导致内存累积",
        "异步操作缺少超时和错误处理",
        "缺少进程管理：没有正确管理与GeoGebra应用的交互进程"
      ],
      "code_issues": [
        "generateGeoGebraImage函数生成了Canvas图像但从未实际保存到文件系统",
        "缺少与本地GeoGebra应用程序的集成",
        "异步操作处理不当，Canvas操作可能导致事件循环阻塞"
      ]
    },
    "solutions": {
      "fixes_applied": [
        "添加了文件系统操作模块：fs, child_process",
        "使用Promise包装Canvas操作，避免阻塞主线程",
        "添加了超时处理和错误边界",
        "实现了实际的文件保存功能",
        "集成了本地GeoGebra应用程序调用",
        "新增launch_geogebra工具",
        "增强了generate_geogebra_from_command工具，支持使用本地GeoGebra应用生成高质量图像"
      ],
      "new_functions": [
        "launchGeoGebraWithFile() - 启动本地GeoGebra应用",
        "generateGeoGebraImageWithApp() - 使用GeoGebra应用生成高质量图像"
      ]
    }
  },
  "geogebra_integration_issues": {
    "problem": "生成的geogebra文件无法正常打开",
    "analysis": {
      "file_format": "GeoGebra的.ggb文件是专有二进制格式，不是标准ZIP",
      "technical_barriers": [
        "需要GeoGebra的内部序列化算法",
        "对象ID管理和依赖关系复杂",
        "3D图形数据的二进制编码方式未知"
      ],
      "official_limitations": "官方未公开文件格式规范"
    },
    "solution": {
      "approach": "改为生成包含数学表达式的文本文件",
      "implementation": "用户可直接复制粘贴到GeoGebra中使用",
      "user_guidance": "创建详细的使用说明文档"
    }
  },
  "mcp_service_expansion": {
    "user_query": "你还能做哪些辅助数学教学或学习的mcp服务？要求：看起来完成度高 使用方便 没有各种兼容性问题 不像ggb文件一样打不开或者需要手动输入",
    "new_services_added": [
      {
        "name": "generate_math_visualization",
        "description": "生成数学可视化图表（函数图像、统计图表等）",
        "features": [
          "函数图像：任意数学函数的交互式图表",
          "统计图表：柱状图、折线图、饼图等",
          "几何图形：平面几何和立体几何图形",
          "微积分可视化：导数、积分等概念展示"
        ],
        "output": "HTML文件，可直接在浏览器打开"
      },
      {
        "name": "create_math_exercise",
        "description": "创建数学练习题及答案解析",
        "features": [
          "主题覆盖：代数、几何、微积分、统计、三角函数",
          "难度分级：简单、中等、困难",
          "格式支持：Word、PDF、HTML",
          "包含内容：题目、答案、详细解析"
        ]
      },
      {
        "name": "math_formula_converter",
        "description": "数学公式格式转换（LaTeX、MathML、图片）",
        "features": [
          "格式支持：LaTeX ↔ MathML ↔ 图片 ↔ 文本",
          "一键转换：自动识别和转换公式格式",
          "图片输出：高质量公式图片，可直接插入文档"
        ]
      },
      {
        "name": "generate_math_tutorial",
        "description": "生成分步数学教程",
        "features": [
          "智能内容：根据概念自动生成教程结构",
          "难度适应：初级、中级、高级",
          "丰富内容：包含概念讲解、例题、练习题",
          "多格式输出：Word、PowerPoint、HTML"
        ]
      }
    ],
    "technical_advantages": [
      "零兼容性问题：全部基于标准Web技术",
      "即开即用：生成的文件直接可用，无需额外软件",
      "高度集成：与现有MCP工具无缝配合",
      "专业质量：输出符合教学标准"
    ]
  },
  "demonstration_system": {
    "request": "以高等数学中一元微积分学的内容作为演示，分别生成这四个功能的内容，放在一个大文件夹中，其中四个功能各一个子文件夹",
    "structure": {
      "main_folder": "高等数学演示",
      "subfolders": [
        "1-数学可视化",
        "2-智能练习题", 
        "3-公式转换",
        "4-分步教程"
      ]
    },
    "content_generated": {
      "visualization": {
        "files": [
          "导数可视化：f(x) = x²及其导数f'(x) = 2x",
          "积分可视化：f(x) = sin(x)的积分",
          "极限可视化：sin(x)/x在x→0时的极限行为",
          "总览页面：整合所有可视化演示"
        ],
        "format": "HTML + PNG图像"
      },
      "exercises": {
        "types": ["导数练习题", "积分练习题", "极限练习题", "应用题"],
        "count_per_type": 5,
        "difficulty_levels": ["简单", "中等", "困难"],
        "format": "HTML + RTF (Word兼容)"
      },
      "formula_conversion": {
        "core_formulas": 10,
        "categories": ["导数公式", "积分公式", "极限公式", "级数公式"],
        "formats": ["LaTeX", "MathML", "文本", "图片"],
        "features": ["交互式标签页", "响应式设计", "MathJax渲染"]
      },
      "tutorials": {
        "topics": ["导数教程", "积分教程", "极限教程", "综合应用"],
        "structure": ["概念讲解", "例题演示", "练习题"],
        "level": "中级",
        "format": "HTML"
      }
    }
  },
  "technical_implementation": {
    "dependencies_added": [
      "archiver": "用于创建ZIP文件",
      "mathjs": "用于数学表达式计算"
    ],
    "code_improvements": [
      "添加了文件系统操作模块",
      "优化了异步操作处理",
      "改进了错误处理机制",
      "增强了Canvas操作"
    ],
    "file_formats": {
      "supported": ["HTML", "PNG", "RTF", "TXT", "JSON"],
      "avoided": ["专有二进制格式如.ggb"],
      "reason": "确保零兼容性问题"
    }
  },
  "final_package": {
    "folder_name": "AI智能体辅助数学教学工具",
    "contents": {
      "core_files": [
        "server.js",
        "package.json", 
        "conversation_context.json"
      ],
      "demonstration": "高等数学演示/ (完整演示内容)",
      "debug_records": "调试记录/ (聊天记录和JSON文件)"
    },
    "usage_instructions": {
      "mcp_service": "运行 npm start 启动服务",
      "demonstration": "打开高等数学演示文件夹，双击HTML文件即可查看",
      "exercises": "支持直接打印或转换为PDF",
      "formulas": "可在浏览器中查看多种格式转换"
    }
  },
  "success_metrics": {
    "problem_resolution": "成功解决了Canvas操作阻塞和GeoGebra文件兼容性问题",
    "functionality_expansion": "从单一GeoGebra集成扩展为4大数学教学功能",
    "user_experience": "创建了完整的演示系统，所有功能即开即用",
    "technical_quality": "零兼容性问题，基于标准Web技术",
    "educational_value": "涵盖一元微积分核心内容，适合教学使用"
  },
  "lessons_learned": {
    "technical": [
      "专有文件格式集成需要谨慎评估",
      "异步操作在Windows环境下的特殊处理",
      "用户体验比技术炫酷更重要"
    ],
    "development": [
      "及时响应用户反馈的重要性",
      "从问题中发现新机会",
      "完整演示系统的价值"
    ]
  },
  "future_improvements": {
    "potential_enhancements": [
      "添加更多数学主题支持",
      "集成在线数学计算引擎",
      "支持协作学习功能",
      "添加学习进度跟踪"
    ],
    "technical_debt": [
      "优化Canvas性能",
      "增强错误恢复机制",
      "改进用户界面设计"
    ]
  }
}